certbot_dns_wedos/__init__.py
certbot_dns_wedos/dns_wedos.py
certbot_dns_wedos-2.4.dist-info/LICENSE
certbot_dns_wedos-2.4.dist-info/METADATA
certbot_dns_wedos-2.4.dist-info/WHEEL
certbot_dns_wedos-2.4.dist-info/entry_points.txt
certbot_dns_wedos-2.4.dist-info/top_level.txt
certbot_dns_wedos-2.4.dist-info/RECORD
