Metadata-Version: 2.2
Name: certbot-dns-wedos
Version: 2.4
Summary: Wedos DNS Authenticator plugin for Certbot
Home-page: https://github.com/clazzor/certbot-dns-wedos
Author: Clazzor
License: Apache License 2.0
Classifier: Development Status :: 5 - Production/Stable
Classifier: Environment :: Plugins
Classifier: Intended Audience :: System Administrators
Classifier: License :: OSI Approved :: Apache Software License
Classifier: Operating System :: POSIX :: Linux
Classifier: Programming Language :: Python
Classifier: Programming Language :: Python :: 3
Classifier: Programming Language :: Python :: 3.9
Classifier: Programming Language :: Python :: 3.10
Classifier: Programming Language :: Python :: 3.11
Classifier: Programming Language :: Python :: 3.12
Classifier: Programming Language :: Python :: 3.13
Classifier: Topic :: Internet :: WWW/HTTP
Classifier: Topic :: Security
Classifier: Topic :: System :: Installation/Setup
Classifier: Topic :: System :: Networking
Classifier: Topic :: System :: Systems Administration
Classifier: Topic :: Utilities
Requires-Python: >=3.9
License-File: LICENSE
Requires-Dist: certbot>=3.0.0
Requires-Dist: acme>=3.0.0
Requires-Dist: setuptools
Requires-Dist: requests
Requires-Dist: pytz
Dynamic: author
Dynamic: classifier
Dynamic: description
Dynamic: description-content-type
Dynamic: home-page
Dynamic: license
Dynamic: requires-dist
Dynamic: requires-python
Dynamic: summary
